forth_kernel/__init__.py
forth_kernel/__main__.py
forth_kernel/forth_kernel.py
forth_kernel/py.typed
forth_kernel/self_install.py
forth_kernel-0.4.1.dist-info/LICENSE
forth_kernel-0.4.1.dist-info/METADATA
forth_kernel-0.4.1.dist-info/WHEEL
forth_kernel-0.4.1.dist-info/top_level.txt
forth_kernel-0.4.1.dist-info/RECORD
