Metadata-Version: 2.2
Name: forth_kernel
Version: 0.4.1
Summary: A Jupyter kernel for the Forth programming language. Allows running Forth in interactive Jupyter Notebook.
Author-email: Sohang Chopra <sohangchopra@gmail.com>
Project-URL: Source, https://github.com/sohang3112/iforth
Classifier: Framework :: IPython
Classifier: License :: OSI Approved :: BSD License
Classifier: Programming Language :: Python :: 3
Classifier: Topic :: System :: Shells
Requires-Python: >=3.8
License-File: LICENSE
Requires-Dist: importlib-metadata>=8.5.0
Requires-Dist: ipykernel>=6.29.5
Requires-Dist: jupyter-client>=8.6.3
Requires-Dist: pexpect>=4.9.0
